sevsd/__init__.py
sevsd/do_work.py
sevsd/generate_image.py
sevsd/load_embeddings.py
sevsd/process_task.py
sevsd/setup_device.py
sevsd/setup_pipeline.py
sevsd-0.5.0.dist-info/LICENSE
sevsd-0.5.0.dist-info/METADATA
sevsd-0.5.0.dist-info/WHEEL
sevsd-0.5.0.dist-info/top_level.txt
sevsd-0.5.0.dist-info/RECORD
