Metadata-Version: 2.1
Name: sevsd
Version: 0.5.0
Summary: A Python package to make Stable Diffusion Image Generation ridiculously easy
Home-page: https://github.com/leopedroso45/Stable-Diffusion-ImageGen
Author: Leonardo Severo
Author-email: leopedroso45@gmail.com
Keywords: image generation,stable diffusion,AI
Classifier: Programming Language :: Python :: 3
Classifier: License :: OSI Approved :: MIT License
Classifier: Operating System :: OS Independent
Requires-Python: >=3.11
License-File: LICENSE
Requires-Dist: torch
Requires-Dist: diffusers
Requires-Dist: transformers
Requires-Dist: omegaconf
Requires-Dist: peft >=0.11.0
Requires-Dist: setuptools
